MANIFEST.in
README.rst
requirements.txt
setup.py
mergeit/__init__.py
mergeit.egg-info/PKG-INFO
mergeit.egg-info/SOURCES.txt
mergeit.egg-info/dependency_links.txt
mergeit.egg-info/entry_points.txt
mergeit.egg-info/requires.txt
mergeit.egg-info/top_level.txt
mergeit/core/__init__.py
mergeit/core/exceptions.py
mergeit/core/push_handler.py
mergeit/core/repo_manager.py
mergeit/core/runner.py
mergeit/core/safe_dict.py
mergeit/core/shell.py
mergeit/core/config/__init__.py
mergeit/core/config/config.py
mergeit/core/config/config_source.py
mergeit/core/config/yaml_config_source.py
mergeit/extras/__init__.py
mergeit/extras/api/__init__.py
mergeit/extras/api/gitlab_api.py
mergeit/extras/filters/__init__.py
mergeit/extras/filters/merge_cmd_filter.py
mergeit/extras/filters/merge_request_gitlab_filter.py
mergeit/extras/filters/next_version_filter.py
mergeit/extras/filters/redmine_filter.py
mergeit/extras/filters/resolve_redmine_filter.py
mergeit/extras/filters/tests_filter.py
mergeit/extras/filters/version_redmine_filter.py
mergeit/extras/hooks/__init__.py
mergeit/extras/hooks/conflict_merge_request_gitlab_hook.py
mergeit/overrides/__init__.py
mergeit/overrides/cmd_telsh.py
mergeit/overrides/logging_extras.py
mergeit/scripts/__init__.py
mergeit/scripts/common.py
mergeit/scripts/server.py
mergeit/scripts/shell.py