Metadata-Version: 1.0
Name: mergeit
Version: 0.1.0
Summary: GIT auto merge tool with branch dependencies, merge preprocessing and hooks
Home-page: https://github.com/insolite/mergeit
Author: Oleg Krasnikov
Author-email: a.insolite@gmail.com
License: UNKNOWN
Platform: UNKNOWN
